kobart_transformers/__init__.py
kobart_transformers/load_model.py
kobart_transformers-0.1.4.dist-info/METADATA
kobart_transformers-0.1.4.dist-info/WHEEL
kobart_transformers-0.1.4.dist-info/top_level.txt
kobart_transformers-0.1.4.dist-info/RECORD
