Metadata-Version: 2.1
Name: kobart-transformers
Version: 0.1.4
Summary: Kobart model on huggingface transformers
Home-page: https://github.com/hyunwoongko/kobart-transformers
Author: Hyunwoong Ko
Author-email: kevin.woong@kakaobrain.com
License: BSD 3-Clause "New" or "Revised" License
Keywords: kobart,huggingface,deep learning
Platform: any
Classifier: Programming Language :: Python :: 3
Classifier: Programming Language :: Python :: 3.2
Classifier: Programming Language :: Python :: 3.3
Classifier: Programming Language :: Python :: 3.4
Classifier: Programming Language :: Python :: 3.5
Classifier: Programming Language :: Python :: 3.6
Classifier: Programming Language :: Python :: 3.7
Classifier: Programming Language :: Python :: 3.8
Requires-Python: >=3
